.installed.cfg
.mr.developer.cfg
.travis.yml
MANIFEST.in
Makefile
README.rst
bootstrap.py
buildout.cfg
setup.py
buildout.d/base.cfg
buildout.d/development.cfg
buildout.d/travis.cfg
buildout.d/versions.cfg
docs/CHANGELOG.rst
docs/api.rst
docs/conf.py
docs/glossary.rst
docs/index.rst
parts/omelette/plone/hud/__init__.py
parts/omelette/plone/hud/configure.zcml
parts/omelette/plone/hud/interfaces.py
parts/omelette/plone/hud/misc.py
parts/omelette/plone/hud/panel.py
parts/omelette/plone/hud/testing.py
parts/omelette/plone/hud/browser/__init__.py
parts/omelette/plone/hud/browser/configure.zcml
parts/omelette/plone/hud/browser/templates/listportlet.pt
parts/omelette/plone/hud/browser/templates/panel.pt
parts/omelette/plone/hud/profiles/default/browserlayer.xml
parts/omelette/plone/hud/profiles/default/controlpanel.xml
parts/omelette/plone/hud/profiles/default/metadata.xml
parts/omelette/plone/hud/tests/__init__.py
parts/omelette/plone/hud/tests/test_misc.py
parts/omelette/plone/hud/tests/test_panel.py
parts/omelette/plone/hud/tests/test_setup.py
parts/omelette/plone/hud/tests/test_utils.py
src/plone/__init__.py
src/plone/__init__.pyc
src/plone.hud.egg-info/PKG-INFO
src/plone.hud.egg-info/SOURCES.txt
src/plone.hud.egg-info/dependency_links.txt
src/plone.hud.egg-info/entry_points.txt
src/plone.hud.egg-info/namespace_packages.txt
src/plone.hud.egg-info/not-zip-safe
src/plone.hud.egg-info/requires.txt
src/plone.hud.egg-info/top_level.txt
src/plone/hud/__init__.py
src/plone/hud/__init__.pyc
src/plone/hud/configure.zcml
src/plone/hud/interfaces.py
src/plone/hud/interfaces.pyc
src/plone/hud/misc.py
src/plone/hud/misc.pyc
src/plone/hud/panel.py
src/plone/hud/panel.pyc
src/plone/hud/testing.py
src/plone/hud/testing.pyc
src/plone/hud/browser/__init__.py
src/plone/hud/browser/__init__.pyc
src/plone/hud/browser/configure.zcml
src/plone/hud/browser/templates/listportlet.pt
src/plone/hud/browser/templates/panel.pt
src/plone/hud/profiles/default/browserlayer.xml
src/plone/hud/profiles/default/controlpanel.xml
src/plone/hud/profiles/default/metadata.xml
src/plone/hud/tests/__init__.py
src/plone/hud/tests/__init__.pyc
src/plone/hud/tests/test_misc.py
src/plone/hud/tests/test_misc.pyc
src/plone/hud/tests/test_panel.py
src/plone/hud/tests/test_panel.pyc
src/plone/hud/tests/test_setup.py
