Metadata-Version: 1.1
Name: plone.hud
Version: 1.0a1
Summary: Plone Heads Up Display Framework
Home-page: http://pypi.python.org/pypi/plone.hud
Author: Plone Foundation
Author-email: plone-developers@lists.sourceforge.net
License: GPL version 2
Keywords: Plone HUD
Platform: UNKNOWN
Classifier: Framework :: Plone
Classifier: Programming Language :: Python
Classifier: Environment :: Web Environment
Classifier: Operating System :: OS Independent
Classifier: Development Status :: 3 - Alpha
